[
null,
{"id":1,"expanded":false,"name":"民家1","order":5,"parentId":0,"scrollX":1080,"scrollY":612},
{"id":2,"expanded":false,"name":"フォルテの家","order":4,"parentId":0,"scrollX":1080,"scrollY":612},
{"id":3,"expanded":false,"name":"ノワール城","order":3,"parentId":0,"scrollX":1064,"scrollY":1356},
{"id":4,"expanded":false,"name":"魔王ノワールの部屋","order":1,"parentId":0,"scrollX":1064,"scrollY":750},
{"id":5,"expanded":true,"name":"魔王ノワールの部屋","order":2,"parentId":4,"scrollX":938.6666666666666,"scrollY":887.3333333333334},
{"id":6,"expanded":false,"name":"Xmasダンジョン１","order":6,"parentId":0,"scrollX":710.6666666666666,"scrollY":407.3333333333333},
{"id":7,"expanded":false,"name":"Xmasダンジョン２","order":7,"parentId":6,"scrollX":720,"scrollY":407.3333333333333},
{"id":8,"expanded":false,"name":"Xmasダンジョン３","order":8,"parentId":6,"scrollX":1080,"scrollY":612},
{"id":9,"expanded":false,"name":"Xmasダンジョン４","order":9,"parentId":6,"scrollX":1080,"scrollY":612},
{"id":10,"expanded":false,"name":"Xmasダンジョン５","order":10,"parentId":9,"scrollX":1080,"scrollY":612},
{"id":11,"expanded":false,"name":"Xmasダンジョン６","order":11,"parentId":6,"scrollX":1080,"scrollY":612},
{"id":12,"expanded":false,"name":"Xmasダンジョン７","order":12,"parentId":6,"scrollX":1080,"scrollY":612},
{"id":13,"expanded":false,"name":"Xmasダンジョン８","order":13,"parentId":12,"scrollX":1080,"scrollY":612},
{"id":14,"expanded":false,"name":"Xmasダンジョン１７","order":22,"parentId":0,"scrollX":700,"scrollY":408.6666666666667},
{"id":15,"expanded":false,"name":"Xmasダンジョン１０","order":15,"parentId":22,"scrollX":1080,"scrollY":612},
{"id":16,"expanded":false,"name":"Xmasダンジョン１１","order":16,"parentId":15,"scrollX":832,"scrollY":640},
{"id":17,"expanded":true,"name":"Xmasダンジョン１２","order":17,"parentId":15,"scrollX":832,"scrollY":640},
{"id":18,"expanded":false,"name":"Xmasダンジョン１３","order":18,"parentId":22,"scrollX":1080,"scrollY":612},
{"id":19,"expanded":true,"name":"Xmasダンジョン１４","order":19,"parentId":18,"scrollX":832,"scrollY":640},
{"id":20,"expanded":true,"name":"Xmasダンジョン１５","order":20,"parentId":18,"scrollX":832,"scrollY":640},
{"id":21,"expanded":true,"name":"Xmasダンジョン１６","order":21,"parentId":22,"scrollX":832,"scrollY":640},
{"id":22,"expanded":false,"name":"Xmasダンジョン９","order":14,"parentId":0,"scrollX":700,"scrollY":640.6666666666666},
{"id":23,"expanded":false,"name":"Xmasダンジョン１８","order":23,"parentId":14,"scrollX":720,"scrollY":407.3333333333333},
{"id":24,"expanded":true,"name":"Xmasダンジョン１９","order":24,"parentId":23,"scrollX":1080,"scrollY":612},
{"id":25,"expanded":true,"name":"Xmasダンジョン２０","order":25,"parentId":23,"scrollX":832,"scrollY":640},
{"id":26,"expanded":false,"name":"Xmasダンジョン２１","order":26,"parentId":14,"scrollX":1080,"scrollY":612},
{"id":27,"expanded":false,"name":"Xmasダンジョン２２","order":27,"parentId":26,"scrollX":1080,"scrollY":612},
{"id":28,"expanded":true,"name":"Xmasダンジョン２３","order":28,"parentId":26,"scrollX":1080,"scrollY":612},
{"id":29,"expanded":false,"name":"Xmasダンジョン２４","order":29,"parentId":0,"scrollX":700,"scrollY":408.6666666666667},
{"id":30,"expanded":false,"name":"回想部屋","order":30,"parentId":0,"scrollX":832,"scrollY":640}
]